{
  "_derived": true,
  "_disclaimer": "Derived, unofficial content generated by the Space Law Corpus. NOT the authoritative legal text. See the linked authoritative source and its authentic-language text for anything legally operative.",
  "vocabulary": {
    "freedom_of_exploration_and_use": "Freedom to explore and use outer space by all States; province/benefit of all; freedom of scientific investigation.",
    "non_appropriation": "Outer space and celestial bodies not subject to national appropriation by sovereignty, use, occupation or other means.",
    "peaceful_use_and_non_militarization": "Peaceful purposes; prohibition of WMD/weapons; no military bases; no intentional harmful acts.",
    "state_responsibility_and_supervision": "International responsibility of States for national activities, including authorization and continuing supervision of non-governmental entities.",
    "jurisdiction_and_control": "Retention of jurisdiction and control over space objects and personnel; ownership of objects.",
    "registration": "Registration of space objects in national and UN registries; furnishing of identifying information.",
    "liability_and_damage": "Responsibility/liability for damage caused by space objects; compensation; claims procedures.",
    "rescue_and_return": "Rescue and return of astronauts/personnel in distress; assistance.",
    "abandonment_and_salvage": "Ownership, recovery and return of space objects (and parts) found beyond the launching State's limits.",
    "resource_rights": "Rights over natural resources of celestial bodies; exploitation; common-heritage regime; samples.",
    "environmental_protection_and_debris": "Protection of the space and Earth environment; harmful contamination; space debris mitigation; long-term sustainability.",
    "international_cooperation_and_transparency": "International cooperation; information-sharing; notification; consultation; benefit-sharing; capacity-building; openness.",
    "dispute_settlement_and_consultation": "Consultation and settlement of disputes; claims commissions; arbitration.",
    "safety_of_space_operations": "Safety of operations; conjunction assessment; collision avoidance; re-entry safety; nuclear-power-source and operational safety."
  },
  "index": {
    "freedom_of_exploration_and_use": [
      {
        "corpus_id": "un/ga/res-1962-XVIII",
        "short_title": "Declaration of Legal Principles",
        "version_id": "1963-12-13",
        "unit": "Principle 1"
      },
      {
        "corpus_id": "un/ga/res-1962-XVIII",
        "short_title": "Declaration of Legal Principles",
        "version_id": "1963-12-13",
        "unit": "Principle 2"
      },
      {
        "corpus_id": "un/ga/res-41-65",
        "short_title": "Remote Sensing Principles",
        "version_id": "1986-12-03",
        "unit": "Principle IV"
      },
      {
        "corpus_id": "un/ga/res-51-122",
        "short_title": "Benefits Declaration",
        "version_id": "1996-12-13",
        "unit": "Declaration (whole instrument)"
      },
      {
        "corpus_id": "un/treaty/moon-1979",
        "short_title": "Moon Agreement",
        "version_id": "1979-12-18",
        "unit": "Article 4"
      },
      {
        "corpus_id": "un/treaty/moon-1979",
        "short_title": "Moon Agreement",
        "version_id": "1979-12-18",
        "unit": "Article 6"
      },
      {
        "corpus_id": "un/treaty/moon-1979",
        "short_title": "Moon Agreement",
        "version_id": "1979-12-18",
        "unit": "Article 8"
      },
      {
        "corpus_id": "un/treaty/ost-1967",
        "short_title": "Outer Space Treaty",
        "version_id": "1967-01-27",
        "unit": "Article I"
      }
    ],
    "non_appropriation": [
      {
        "corpus_id": "un/ga/res-1962-XVIII",
        "short_title": "Declaration of Legal Principles",
        "version_id": "1963-12-13",
        "unit": "Principle 1"
      },
      {
        "corpus_id": "un/ga/res-1962-XVIII",
        "short_title": "Declaration of Legal Principles",
        "version_id": "1963-12-13",
        "unit": "Principle 3"
      },
      {
        "corpus_id": "un/ga/res-51-122",
        "short_title": "Benefits Declaration",
        "version_id": "1996-12-13",
        "unit": "Declaration (whole instrument)"
      },
      {
        "corpus_id": "un/treaty/moon-1979",
        "short_title": "Moon Agreement",
        "version_id": "1979-12-18",
        "unit": "Article 11"
      },
      {
        "corpus_id": "un/treaty/ost-1967",
        "short_title": "Outer Space Treaty",
        "version_id": "1967-01-27",
        "unit": "Article I"
      },
      {
        "corpus_id": "un/treaty/ost-1967",
        "short_title": "Outer Space Treaty",
        "version_id": "1967-01-27",
        "unit": "Article II"
      }
    ],
    "peaceful_use_and_non_militarization": [
      {
        "corpus_id": "un/ga/res-1962-XVIII",
        "short_title": "Declaration of Legal Principles",
        "version_id": "1963-12-13",
        "unit": "Principle 4"
      },
      {
        "corpus_id": "un/ga/res-37-92",
        "short_title": "Direct Broadcasting Principles",
        "version_id": "1982-12-10",
        "unit": "Direct Broadcasting principles (whole instrument)"
      },
      {
        "corpus_id": "un/softlaw/copuos-debris-mitigation-2007",
        "short_title": "COPUOS Space Debris Mitigation Guidelines",
        "version_id": "2007-06-15",
        "unit": "Guideline 4"
      },
      {
        "corpus_id": "un/treaty/moon-1979",
        "short_title": "Moon Agreement",
        "version_id": "1979-12-18",
        "unit": "Article 2"
      },
      {
        "corpus_id": "un/treaty/moon-1979",
        "short_title": "Moon Agreement",
        "version_id": "1979-12-18",
        "unit": "Article 3"
      },
      {
        "corpus_id": "un/treaty/ost-1967",
        "short_title": "Outer Space Treaty",
        "version_id": "1967-01-27",
        "unit": "Article III"
      },
      {
        "corpus_id": "un/treaty/ost-1967",
        "short_title": "Outer Space Treaty",
        "version_id": "1967-01-27",
        "unit": "Article IV"
      }
    ],
    "state_responsibility_and_supervision": [
      {
        "corpus_id": "un/ga/res-1962-XVIII",
        "short_title": "Declaration of Legal Principles",
        "version_id": "1963-12-13",
        "unit": "Principle 5"
      },
      {
        "corpus_id": "un/ga/res-37-92",
        "short_title": "Direct Broadcasting Principles",
        "version_id": "1982-12-10",
        "unit": "Direct Broadcasting principles (whole instrument)"
      },
      {
        "corpus_id": "un/ga/res-41-65",
        "short_title": "Remote Sensing Principles",
        "version_id": "1986-12-03",
        "unit": "Principle XIV"
      },
      {
        "corpus_id": "un/ga/res-47-68",
        "short_title": "Nuclear Power Sources Principles",
        "version_id": "1992-12-14",
        "unit": "Principle 8"
      },
      {
        "corpus_id": "un/softlaw/lts-guidelines-2019",
        "short_title": "LTS Guidelines",
        "version_id": "2019-06-21",
        "unit": "Guideline A.1"
      },
      {
        "corpus_id": "un/softlaw/lts-guidelines-2019",
        "short_title": "LTS Guidelines",
        "version_id": "2019-06-21",
        "unit": "Guideline A.2"
      },
      {
        "corpus_id": "un/softlaw/lts-guidelines-2019",
        "short_title": "LTS Guidelines",
        "version_id": "2019-06-21",
        "unit": "Guideline A.3"
      },
      {
        "corpus_id": "un/treaty/liability-1972",
        "short_title": "Liability Convention",
        "version_id": "1972-03-29",
        "unit": "Article XXII"
      },
      {
        "corpus_id": "un/treaty/moon-1979",
        "short_title": "Moon Agreement",
        "version_id": "1979-12-18",
        "unit": "Article 14"
      },
      {
        "corpus_id": "un/treaty/moon-1979",
        "short_title": "Moon Agreement",
        "version_id": "1979-12-18",
        "unit": "Article 16"
      },
      {
        "corpus_id": "un/treaty/ost-1967",
        "short_title": "Outer Space Treaty",
        "version_id": "1967-01-27",
        "unit": "Article VI"
      },
      {
        "corpus_id": "un/treaty/ost-1967",
        "short_title": "Outer Space Treaty",
        "version_id": "1967-01-27",
        "unit": "Article XIII"
      },
      {
        "corpus_id": "un/treaty/registration-1975",
        "short_title": "Registration Convention",
        "version_id": "1975-01-14",
        "unit": "Article VII"
      },
      {
        "corpus_id": "un/treaty/rescue-1968",
        "short_title": "Rescue Agreement",
        "version_id": "1968-04-22",
        "unit": "Article 6"
      }
    ],
    "jurisdiction_and_control": [
      {
        "corpus_id": "un/ga/res-1962-XVIII",
        "short_title": "Declaration of Legal Principles",
        "version_id": "1963-12-13",
        "unit": "Principle 7"
      },
      {
        "corpus_id": "un/treaty/moon-1979",
        "short_title": "Moon Agreement",
        "version_id": "1979-12-18",
        "unit": "Article 9"
      },
      {
        "corpus_id": "un/treaty/moon-1979",
        "short_title": "Moon Agreement",
        "version_id": "1979-12-18",
        "unit": "Article 12"
      },
      {
        "corpus_id": "un/treaty/ost-1967",
        "short_title": "Outer Space Treaty",
        "version_id": "1967-01-27",
        "unit": "Article VIII"
      }
    ],
    "registration": [
      {
        "corpus_id": "un/softlaw/lts-guidelines-2019",
        "short_title": "LTS Guidelines",
        "version_id": "2019-06-21",
        "unit": "Guideline A.5"
      },
      {
        "corpus_id": "un/treaty/registration-1975",
        "short_title": "Registration Convention",
        "version_id": "1975-01-14",
        "unit": "Article I"
      },
      {
        "corpus_id": "un/treaty/registration-1975",
        "short_title": "Registration Convention",
        "version_id": "1975-01-14",
        "unit": "Article II"
      },
      {
        "corpus_id": "un/treaty/registration-1975",
        "short_title": "Registration Convention",
        "version_id": "1975-01-14",
        "unit": "Article III"
      },
      {
        "corpus_id": "un/treaty/registration-1975",
        "short_title": "Registration Convention",
        "version_id": "1975-01-14",
        "unit": "Article IV"
      },
      {
        "corpus_id": "un/treaty/registration-1975",
        "short_title": "Registration Convention",
        "version_id": "1975-01-14",
        "unit": "Article V"
      },
      {
        "corpus_id": "un/treaty/registration-1975",
        "short_title": "Registration Convention",
        "version_id": "1975-01-14",
        "unit": "Article VI"
      },
      {
        "corpus_id": "un/treaty/registration-1975",
        "short_title": "Registration Convention",
        "version_id": "1975-01-14",
        "unit": "Article VII"
      }
    ],
    "liability_and_damage": [
      {
        "corpus_id": "un/ga/res-1962-XVIII",
        "short_title": "Declaration of Legal Principles",
        "version_id": "1963-12-13",
        "unit": "Principle 8"
      },
      {
        "corpus_id": "un/ga/res-47-68",
        "short_title": "Nuclear Power Sources Principles",
        "version_id": "1992-12-14",
        "unit": "Principle 9"
      },
      {
        "corpus_id": "un/treaty/liability-1972",
        "short_title": "Liability Convention",
        "version_id": "1972-03-29",
        "unit": "Article I"
      },
      {
        "corpus_id": "un/treaty/liability-1972",
        "short_title": "Liability Convention",
        "version_id": "1972-03-29",
        "unit": "Article II"
      },
      {
        "corpus_id": "un/treaty/liability-1972",
        "short_title": "Liability Convention",
        "version_id": "1972-03-29",
        "unit": "Article III"
      },
      {
        "corpus_id": "un/treaty/liability-1972",
        "short_title": "Liability Convention",
        "version_id": "1972-03-29",
        "unit": "Article IV"
      },
      {
        "corpus_id": "un/treaty/liability-1972",
        "short_title": "Liability Convention",
        "version_id": "1972-03-29",
        "unit": "Article V"
      },
      {
        "corpus_id": "un/treaty/liability-1972",
        "short_title": "Liability Convention",
        "version_id": "1972-03-29",
        "unit": "Article VI"
      },
      {
        "corpus_id": "un/treaty/liability-1972",
        "short_title": "Liability Convention",
        "version_id": "1972-03-29",
        "unit": "Article VII"
      },
      {
        "corpus_id": "un/treaty/liability-1972",
        "short_title": "Liability Convention",
        "version_id": "1972-03-29",
        "unit": "Article VIII"
      },
      {
        "corpus_id": "un/treaty/liability-1972",
        "short_title": "Liability Convention",
        "version_id": "1972-03-29",
        "unit": "Article IX"
      },
      {
        "corpus_id": "un/treaty/liability-1972",
        "short_title": "Liability Convention",
        "version_id": "1972-03-29",
        "unit": "Article X"
      },
      {
        "corpus_id": "un/treaty/liability-1972",
        "short_title": "Liability Convention",
        "version_id": "1972-03-29",
        "unit": "Article XI"
      },
      {
        "corpus_id": "un/treaty/liability-1972",
        "short_title": "Liability Convention",
        "version_id": "1972-03-29",
        "unit": "Article XII"
      },
      {
        "corpus_id": "un/treaty/liability-1972",
        "short_title": "Liability Convention",
        "version_id": "1972-03-29",
        "unit": "Article XVIII"
      },
      {
        "corpus_id": "un/treaty/liability-1972",
        "short_title": "Liability Convention",
        "version_id": "1972-03-29",
        "unit": "Article XXI"
      },
      {
        "corpus_id": "un/treaty/liability-1972",
        "short_title": "Liability Convention",
        "version_id": "1972-03-29",
        "unit": "Article XXII"
      },
      {
        "corpus_id": "un/treaty/ost-1967",
        "short_title": "Outer Space Treaty",
        "version_id": "1967-01-27",
        "unit": "Article VII"
      },
      {
        "corpus_id": "un/treaty/rescue-1968",
        "short_title": "Rescue Agreement",
        "version_id": "1968-04-22",
        "unit": "Article 5"
      }
    ],
    "rescue_and_return": [
      {
        "corpus_id": "un/ga/res-1962-XVIII",
        "short_title": "Declaration of Legal Principles",
        "version_id": "1963-12-13",
        "unit": "Principle 9"
      },
      {
        "corpus_id": "un/treaty/moon-1979",
        "short_title": "Moon Agreement",
        "version_id": "1979-12-18",
        "unit": "Article 10"
      },
      {
        "corpus_id": "un/treaty/ost-1967",
        "short_title": "Outer Space Treaty",
        "version_id": "1967-01-27",
        "unit": "Article V"
      },
      {
        "corpus_id": "un/treaty/rescue-1968",
        "short_title": "Rescue Agreement",
        "version_id": "1968-04-22",
        "unit": "Article 1"
      },
      {
        "corpus_id": "un/treaty/rescue-1968",
        "short_title": "Rescue Agreement",
        "version_id": "1968-04-22",
        "unit": "Article 2"
      },
      {
        "corpus_id": "un/treaty/rescue-1968",
        "short_title": "Rescue Agreement",
        "version_id": "1968-04-22",
        "unit": "Article 3"
      },
      {
        "corpus_id": "un/treaty/rescue-1968",
        "short_title": "Rescue Agreement",
        "version_id": "1968-04-22",
        "unit": "Article 4"
      }
    ],
    "abandonment_and_salvage": [
      {
        "corpus_id": "un/ga/res-1962-XVIII",
        "short_title": "Declaration of Legal Principles",
        "version_id": "1963-12-13",
        "unit": "Principle 7"
      },
      {
        "corpus_id": "un/treaty/ost-1967",
        "short_title": "Outer Space Treaty",
        "version_id": "1967-01-27",
        "unit": "Article VIII"
      },
      {
        "corpus_id": "un/treaty/registration-1975",
        "short_title": "Registration Convention",
        "version_id": "1975-01-14",
        "unit": "Article VI"
      },
      {
        "corpus_id": "un/treaty/rescue-1968",
        "short_title": "Rescue Agreement",
        "version_id": "1968-04-22",
        "unit": "Article 5"
      }
    ],
    "resource_rights": [
      {
        "corpus_id": "un/ga/res-41-65",
        "short_title": "Remote Sensing Principles",
        "version_id": "1986-12-03",
        "unit": "Principle XII"
      },
      {
        "corpus_id": "un/treaty/moon-1979",
        "short_title": "Moon Agreement",
        "version_id": "1979-12-18",
        "unit": "Article 6"
      },
      {
        "corpus_id": "un/treaty/moon-1979",
        "short_title": "Moon Agreement",
        "version_id": "1979-12-18",
        "unit": "Article 11"
      }
    ],
    "environmental_protection_and_debris": [
      {
        "corpus_id": "un/ga/res-1962-XVIII",
        "short_title": "Declaration of Legal Principles",
        "version_id": "1963-12-13",
        "unit": "Principle 6"
      },
      {
        "corpus_id": "un/ga/res-41-65",
        "short_title": "Remote Sensing Principles",
        "version_id": "1986-12-03",
        "unit": "Principle X"
      },
      {
        "corpus_id": "un/ga/res-41-65",
        "short_title": "Remote Sensing Principles",
        "version_id": "1986-12-03",
        "unit": "Principle XI"
      },
      {
        "corpus_id": "un/ga/res-47-68",
        "short_title": "Nuclear Power Sources Principles",
        "version_id": "1992-12-14",
        "unit": "Principle 2"
      },
      {
        "corpus_id": "un/ga/res-47-68",
        "short_title": "Nuclear Power Sources Principles",
        "version_id": "1992-12-14",
        "unit": "Principle 3"
      },
      {
        "corpus_id": "un/softlaw/copuos-debris-mitigation-2007",
        "short_title": "COPUOS Space Debris Mitigation Guidelines",
        "version_id": "2007-06-15",
        "unit": "Guideline 1"
      },
      {
        "corpus_id": "un/softlaw/copuos-debris-mitigation-2007",
        "short_title": "COPUOS Space Debris Mitigation Guidelines",
        "version_id": "2007-06-15",
        "unit": "Guideline 2"
      },
      {
        "corpus_id": "un/softlaw/copuos-debris-mitigation-2007",
        "short_title": "COPUOS Space Debris Mitigation Guidelines",
        "version_id": "2007-06-15",
        "unit": "Guideline 3"
      },
      {
        "corpus_id": "un/softlaw/copuos-debris-mitigation-2007",
        "short_title": "COPUOS Space Debris Mitigation Guidelines",
        "version_id": "2007-06-15",
        "unit": "Guideline 4"
      },
      {
        "corpus_id": "un/softlaw/copuos-debris-mitigation-2007",
        "short_title": "COPUOS Space Debris Mitigation Guidelines",
        "version_id": "2007-06-15",
        "unit": "Guideline 5"
      },
      {
        "corpus_id": "un/softlaw/copuos-debris-mitigation-2007",
        "short_title": "COPUOS Space Debris Mitigation Guidelines",
        "version_id": "2007-06-15",
        "unit": "Guideline 6"
      },
      {
        "corpus_id": "un/softlaw/copuos-debris-mitigation-2007",
        "short_title": "COPUOS Space Debris Mitigation Guidelines",
        "version_id": "2007-06-15",
        "unit": "Guideline 7"
      },
      {
        "corpus_id": "un/softlaw/lts-guidelines-2019",
        "short_title": "LTS Guidelines",
        "version_id": "2019-06-21",
        "unit": "Guideline B.3"
      },
      {
        "corpus_id": "un/softlaw/lts-guidelines-2019",
        "short_title": "LTS Guidelines",
        "version_id": "2019-06-21",
        "unit": "Guideline B.8"
      },
      {
        "corpus_id": "un/softlaw/lts-guidelines-2019",
        "short_title": "LTS Guidelines",
        "version_id": "2019-06-21",
        "unit": "Guideline B.9"
      },
      {
        "corpus_id": "un/softlaw/lts-guidelines-2019",
        "short_title": "LTS Guidelines",
        "version_id": "2019-06-21",
        "unit": "Guideline D.2"
      },
      {
        "corpus_id": "un/treaty/moon-1979",
        "short_title": "Moon Agreement",
        "version_id": "1979-12-18",
        "unit": "Article 7"
      },
      {
        "corpus_id": "un/treaty/ost-1967",
        "short_title": "Outer Space Treaty",
        "version_id": "1967-01-27",
        "unit": "Article IX"
      }
    ],
    "international_cooperation_and_transparency": [
      {
        "corpus_id": "un/ga/res-1962-XVIII",
        "short_title": "Declaration of Legal Principles",
        "version_id": "1963-12-13",
        "unit": "Principle 4"
      },
      {
        "corpus_id": "un/ga/res-1962-XVIII",
        "short_title": "Declaration of Legal Principles",
        "version_id": "1963-12-13",
        "unit": "Principle 6"
      },
      {
        "corpus_id": "un/ga/res-37-92",
        "short_title": "Direct Broadcasting Principles",
        "version_id": "1982-12-10",
        "unit": "Direct Broadcasting principles (whole instrument)"
      },
      {
        "corpus_id": "un/ga/res-41-65",
        "short_title": "Remote Sensing Principles",
        "version_id": "1986-12-03",
        "unit": "Principle IV"
      },
      {
        "corpus_id": "un/ga/res-41-65",
        "short_title": "Remote Sensing Principles",
        "version_id": "1986-12-03",
        "unit": "Principle XI"
      },
      {
        "corpus_id": "un/ga/res-41-65",
        "short_title": "Remote Sensing Principles",
        "version_id": "1986-12-03",
        "unit": "Principle XII"
      },
      {
        "corpus_id": "un/ga/res-41-65",
        "short_title": "Remote Sensing Principles",
        "version_id": "1986-12-03",
        "unit": "Principle XIII"
      },
      {
        "corpus_id": "un/ga/res-47-68",
        "short_title": "Nuclear Power Sources Principles",
        "version_id": "1992-12-14",
        "unit": "Principle 5"
      },
      {
        "corpus_id": "un/ga/res-47-68",
        "short_title": "Nuclear Power Sources Principles",
        "version_id": "1992-12-14",
        "unit": "Principle 6"
      },
      {
        "corpus_id": "un/ga/res-47-68",
        "short_title": "Nuclear Power Sources Principles",
        "version_id": "1992-12-14",
        "unit": "Principle 7"
      },
      {
        "corpus_id": "un/ga/res-51-122",
        "short_title": "Benefits Declaration",
        "version_id": "1996-12-13",
        "unit": "Declaration (whole instrument)"
      },
      {
        "corpus_id": "un/softlaw/lts-guidelines-2019",
        "short_title": "LTS Guidelines",
        "version_id": "2019-06-21",
        "unit": "Guideline A.4"
      },
      {
        "corpus_id": "un/softlaw/lts-guidelines-2019",
        "short_title": "LTS Guidelines",
        "version_id": "2019-06-21",
        "unit": "Guideline B.1"
      },
      {
        "corpus_id": "un/softlaw/lts-guidelines-2019",
        "short_title": "LTS Guidelines",
        "version_id": "2019-06-21",
        "unit": "Guideline B.2"
      },
      {
        "corpus_id": "un/softlaw/lts-guidelines-2019",
        "short_title": "LTS Guidelines",
        "version_id": "2019-06-21",
        "unit": "Guideline B.3"
      },
      {
        "corpus_id": "un/softlaw/lts-guidelines-2019",
        "short_title": "LTS Guidelines",
        "version_id": "2019-06-21",
        "unit": "Guideline C.1"
      },
      {
        "corpus_id": "un/softlaw/lts-guidelines-2019",
        "short_title": "LTS Guidelines",
        "version_id": "2019-06-21",
        "unit": "Guideline C.2"
      },
      {
        "corpus_id": "un/softlaw/lts-guidelines-2019",
        "short_title": "LTS Guidelines",
        "version_id": "2019-06-21",
        "unit": "Guideline C.3"
      },
      {
        "corpus_id": "un/softlaw/lts-guidelines-2019",
        "short_title": "LTS Guidelines",
        "version_id": "2019-06-21",
        "unit": "Guideline C.4"
      },
      {
        "corpus_id": "un/softlaw/lts-guidelines-2019",
        "short_title": "LTS Guidelines",
        "version_id": "2019-06-21",
        "unit": "Guideline D.1"
      },
      {
        "corpus_id": "un/treaty/liability-1972",
        "short_title": "Liability Convention",
        "version_id": "1972-03-29",
        "unit": "Article XXI"
      },
      {
        "corpus_id": "un/treaty/moon-1979",
        "short_title": "Moon Agreement",
        "version_id": "1979-12-18",
        "unit": "Article 4"
      },
      {
        "corpus_id": "un/treaty/moon-1979",
        "short_title": "Moon Agreement",
        "version_id": "1979-12-18",
        "unit": "Article 5"
      },
      {
        "corpus_id": "un/treaty/moon-1979",
        "short_title": "Moon Agreement",
        "version_id": "1979-12-18",
        "unit": "Article 9"
      },
      {
        "corpus_id": "un/treaty/moon-1979",
        "short_title": "Moon Agreement",
        "version_id": "1979-12-18",
        "unit": "Article 13"
      },
      {
        "corpus_id": "un/treaty/moon-1979",
        "short_title": "Moon Agreement",
        "version_id": "1979-12-18",
        "unit": "Article 15"
      },
      {
        "corpus_id": "un/treaty/ost-1967",
        "short_title": "Outer Space Treaty",
        "version_id": "1967-01-27",
        "unit": "Article I"
      },
      {
        "corpus_id": "un/treaty/ost-1967",
        "short_title": "Outer Space Treaty",
        "version_id": "1967-01-27",
        "unit": "Article III"
      },
      {
        "corpus_id": "un/treaty/ost-1967",
        "short_title": "Outer Space Treaty",
        "version_id": "1967-01-27",
        "unit": "Article V"
      },
      {
        "corpus_id": "un/treaty/ost-1967",
        "short_title": "Outer Space Treaty",
        "version_id": "1967-01-27",
        "unit": "Article IX"
      },
      {
        "corpus_id": "un/treaty/ost-1967",
        "short_title": "Outer Space Treaty",
        "version_id": "1967-01-27",
        "unit": "Article X"
      },
      {
        "corpus_id": "un/treaty/ost-1967",
        "short_title": "Outer Space Treaty",
        "version_id": "1967-01-27",
        "unit": "Article XI"
      },
      {
        "corpus_id": "un/treaty/ost-1967",
        "short_title": "Outer Space Treaty",
        "version_id": "1967-01-27",
        "unit": "Article XII"
      },
      {
        "corpus_id": "un/treaty/ost-1967",
        "short_title": "Outer Space Treaty",
        "version_id": "1967-01-27",
        "unit": "Article XIII"
      },
      {
        "corpus_id": "un/treaty/registration-1975",
        "short_title": "Registration Convention",
        "version_id": "1975-01-14",
        "unit": "Article III"
      },
      {
        "corpus_id": "un/treaty/registration-1975",
        "short_title": "Registration Convention",
        "version_id": "1975-01-14",
        "unit": "Article IV"
      },
      {
        "corpus_id": "un/treaty/registration-1975",
        "short_title": "Registration Convention",
        "version_id": "1975-01-14",
        "unit": "Article VI"
      },
      {
        "corpus_id": "un/treaty/rescue-1968",
        "short_title": "Rescue Agreement",
        "version_id": "1968-04-22",
        "unit": "Article 1"
      },
      {
        "corpus_id": "un/treaty/rescue-1968",
        "short_title": "Rescue Agreement",
        "version_id": "1968-04-22",
        "unit": "Article 5"
      }
    ],
    "dispute_settlement_and_consultation": [
      {
        "corpus_id": "un/ga/res-37-92",
        "short_title": "Direct Broadcasting Principles",
        "version_id": "1982-12-10",
        "unit": "Direct Broadcasting principles (whole instrument)"
      },
      {
        "corpus_id": "un/ga/res-41-65",
        "short_title": "Remote Sensing Principles",
        "version_id": "1986-12-03",
        "unit": "Principle XV"
      },
      {
        "corpus_id": "un/treaty/liability-1972",
        "short_title": "Liability Convention",
        "version_id": "1972-03-29",
        "unit": "Article VIII"
      },
      {
        "corpus_id": "un/treaty/liability-1972",
        "short_title": "Liability Convention",
        "version_id": "1972-03-29",
        "unit": "Article IX"
      },
      {
        "corpus_id": "un/treaty/liability-1972",
        "short_title": "Liability Convention",
        "version_id": "1972-03-29",
        "unit": "Article X"
      },
      {
        "corpus_id": "un/treaty/liability-1972",
        "short_title": "Liability Convention",
        "version_id": "1972-03-29",
        "unit": "Article XI"
      },
      {
        "corpus_id": "un/treaty/liability-1972",
        "short_title": "Liability Convention",
        "version_id": "1972-03-29",
        "unit": "Article XII"
      },
      {
        "corpus_id": "un/treaty/liability-1972",
        "short_title": "Liability Convention",
        "version_id": "1972-03-29",
        "unit": "Article XIV"
      },
      {
        "corpus_id": "un/treaty/liability-1972",
        "short_title": "Liability Convention",
        "version_id": "1972-03-29",
        "unit": "Article XV"
      },
      {
        "corpus_id": "un/treaty/liability-1972",
        "short_title": "Liability Convention",
        "version_id": "1972-03-29",
        "unit": "Article XVIII"
      },
      {
        "corpus_id": "un/treaty/liability-1972",
        "short_title": "Liability Convention",
        "version_id": "1972-03-29",
        "unit": "Article XIX"
      },
      {
        "corpus_id": "un/treaty/moon-1979",
        "short_title": "Moon Agreement",
        "version_id": "1979-12-18",
        "unit": "Article 15"
      },
      {
        "corpus_id": "un/treaty/ost-1967",
        "short_title": "Outer Space Treaty",
        "version_id": "1967-01-27",
        "unit": "Article IX"
      }
    ],
    "safety_of_space_operations": [
      {
        "corpus_id": "un/ga/res-47-68",
        "short_title": "Nuclear Power Sources Principles",
        "version_id": "1992-12-14",
        "unit": "Principle 2"
      },
      {
        "corpus_id": "un/ga/res-47-68",
        "short_title": "Nuclear Power Sources Principles",
        "version_id": "1992-12-14",
        "unit": "Principle 3"
      },
      {
        "corpus_id": "un/ga/res-47-68",
        "short_title": "Nuclear Power Sources Principles",
        "version_id": "1992-12-14",
        "unit": "Principle 4"
      },
      {
        "corpus_id": "un/ga/res-47-68",
        "short_title": "Nuclear Power Sources Principles",
        "version_id": "1992-12-14",
        "unit": "Principle 5"
      },
      {
        "corpus_id": "un/softlaw/copuos-debris-mitigation-2007",
        "short_title": "COPUOS Space Debris Mitigation Guidelines",
        "version_id": "2007-06-15",
        "unit": "Guideline 2"
      },
      {
        "corpus_id": "un/softlaw/copuos-debris-mitigation-2007",
        "short_title": "COPUOS Space Debris Mitigation Guidelines",
        "version_id": "2007-06-15",
        "unit": "Guideline 3"
      },
      {
        "corpus_id": "un/softlaw/lts-guidelines-2019",
        "short_title": "LTS Guidelines",
        "version_id": "2019-06-21",
        "unit": "Guideline A.4"
      },
      {
        "corpus_id": "un/softlaw/lts-guidelines-2019",
        "short_title": "LTS Guidelines",
        "version_id": "2019-06-21",
        "unit": "Guideline B.1"
      },
      {
        "corpus_id": "un/softlaw/lts-guidelines-2019",
        "short_title": "LTS Guidelines",
        "version_id": "2019-06-21",
        "unit": "Guideline B.2"
      },
      {
        "corpus_id": "un/softlaw/lts-guidelines-2019",
        "short_title": "LTS Guidelines",
        "version_id": "2019-06-21",
        "unit": "Guideline B.4"
      },
      {
        "corpus_id": "un/softlaw/lts-guidelines-2019",
        "short_title": "LTS Guidelines",
        "version_id": "2019-06-21",
        "unit": "Guideline B.5"
      },
      {
        "corpus_id": "un/softlaw/lts-guidelines-2019",
        "short_title": "LTS Guidelines",
        "version_id": "2019-06-21",
        "unit": "Guideline B.6"
      },
      {
        "corpus_id": "un/softlaw/lts-guidelines-2019",
        "short_title": "LTS Guidelines",
        "version_id": "2019-06-21",
        "unit": "Guideline B.7"
      },
      {
        "corpus_id": "un/softlaw/lts-guidelines-2019",
        "short_title": "LTS Guidelines",
        "version_id": "2019-06-21",
        "unit": "Guideline B.8"
      },
      {
        "corpus_id": "un/softlaw/lts-guidelines-2019",
        "short_title": "LTS Guidelines",
        "version_id": "2019-06-21",
        "unit": "Guideline B.9"
      },
      {
        "corpus_id": "un/softlaw/lts-guidelines-2019",
        "short_title": "LTS Guidelines",
        "version_id": "2019-06-21",
        "unit": "Guideline B.10"
      },
      {
        "corpus_id": "un/softlaw/lts-guidelines-2019",
        "short_title": "LTS Guidelines",
        "version_id": "2019-06-21",
        "unit": "Guideline D.1"
      }
    ]
  }
}